MLLPStreamingClient/MLLPStreamingClient.py
MLLPStreamingClient/__init__.py
MLLPStreamingClient/mllp_streaming_pb2.py
MLLPStreamingClient/mllp_streaming_pb2_grpc.py
MLLPStreamingClient-1.0.1.data/scripts/mllp-speech-dubbing_file.py
MLLPStreamingClient-1.0.1.data/scripts/mllp-speech-dubbing_mic.py
MLLPStreamingClient-1.0.1.data/scripts/mllp-speech-to-text_file.py
MLLPStreamingClient-1.0.1.data/scripts/mllp-speech-to-text_mic.py
MLLPStreamingClient-1.0.1.data/scripts/mllp-speech-translation_file.py
MLLPStreamingClient-1.0.1.data/scripts/mllp-speech-translation_mic.py
MLLPStreamingClient-1.0.1.data/scripts/mllp-text-to-speech_file.py
MLLPStreamingClient-1.0.1.data/scripts/mllp-text-to-speech_terminal.py
MLLPStreamingClient-1.0.1.data/scripts/mllp-text-to-text_file.py
MLLPStreamingClient-1.0.1.data/scripts/mllp-text-to-text_terminal.py
MLLPStreamingClient-1.0.1.dist-info/LICENSE
MLLPStreamingClient-1.0.1.dist-info/METADATA
MLLPStreamingClient-1.0.1.dist-info/WHEEL
MLLPStreamingClient-1.0.1.dist-info/top_level.txt
MLLPStreamingClient-1.0.1.dist-info/RECORD
