Metadata-Version: 2.1
Name: MLLPStreamingClient
Version: 1.0.1
Summary: The MLLP-TTP gRPC Streaming API Python3 client library
Home-page: https://www.mllp.upv.es
Author: MLLP-VRAIN
Author-email: mllp-support@upv.es
Project-URL: RPC API documentation, https://ttp.mllp.upv.es/mllp-streaming-api/1.0/index.html
Project-URL: Python3 client documentation, https://ttp.mllp.upv.es/mllp-streaming-api/1.0/python3-client-doc.html
Classifier: Development Status :: 5 - Production/Stable
Classifier: Programming Language :: Python :: 3
Classifier: License :: OSI Approved :: Apache Software License
Classifier: Operating System :: OS Independent
Requires-Python: >=3.5
License-File: LICENSE
Requires-Dist: protobuf ==4.25.3
Requires-Dist: grpcio ==1.62.0
Requires-Dist: grpcio-tools ==1.62.0
Requires-Dist: pyaudio
Requires-Dist: soundfile
Requires-Dist: sounddevice
